sharedvault/__init__.py
sharedvault/vault.py
sharedvault-2020.9.6.dist-info/METADATA
sharedvault-2020.9.6.dist-info/WHEEL
sharedvault-2020.9.6.dist-info/top_level.txt
sharedvault-2020.9.6.dist-info/RECORD
