Metadata-Version: 2.1
Name: sharedvault
Version: 2020.9.6
Summary: SharedVault is a small application that allows you to define a secret that will require multiple people to unlock.
Home-page: https://github.com/nanassito/sharedvault
Author: Dorian Jaminais
Author-email: sharedvault@jaminais.fr
License: UNKNOWN
Platform: UNKNOWN
Classifier: Programming Language :: Python :: 3
Classifier: License :: Public Domain
Classifier: Operating System :: OS Independent
Requires-Python: >=3.6
Requires-Dist: argparse-logging
Requires-Dist: cryptography
Requires-Dist: sqlalchemy
Requires-Dist: tabulate
Requires-Dist: pymysql
